ibmc_client/__init__.py
ibmc_client/connector.py
ibmc_client/constants.py
ibmc_client/exceptions.py
ibmc_client/raid_utils.py
ibmc_client/utils.py
ibmc_client/api/__init__.py
ibmc_client/api/chassis/__init__.py
ibmc_client/api/chassis/drive.py
ibmc_client/api/system/__init__.py
ibmc_client/api/system/bios.py
ibmc_client/api/system/storage.py
ibmc_client/api/system/volume.py
ibmc_client/api/task/__init__.py
ibmc_client/api/task/task.py
ibmc_client/resources/__init__.py
ibmc_client/resources/chassis/__init__.py
ibmc_client/resources/chassis/drive.py
ibmc_client/resources/system/__init__.py
ibmc_client/resources/system/bios.py
ibmc_client/resources/system/boot_source_override.py
ibmc_client/resources/system/storage.py
ibmc_client/resources/task/__init__.py
tests/unittests/__init__.py
tests/unittests/test_apply_raid_config_cases.py
tests/unittests/test_chassis.py
tests/unittests/test_connect.py
tests/unittests/test_drive.py
tests/unittests/test_storage.py
tests/unittests/test_system.py
tests/unittests/test_task.py
tests/unittests/test_volume.py
python_ibmcclient-0.2.5.1.dist-info/LICENSE.txt
python_ibmcclient-0.2.5.1.dist-info/METADATA
python_ibmcclient-0.2.5.1.dist-info/WHEEL
python_ibmcclient-0.2.5.1.dist-info/top_level.txt
python_ibmcclient-0.2.5.1.dist-info/RECORD
