Metadata-Version: 2.1
Name: python-ibmcclient
Version: 0.2.5.1
Summary: HUAWEI iBMC client
Home-page: https://github.com/IamFive/python-ibmcclient
Author: QianBiao NG
Author-email: iampurse@vip.qq.com
License: UNKNOWN
Project-URL: Bug Reports, https://github.com/IamFive/python-ibmcclient/issues
Project-URL: Source, https://github.com/IamFive/python-ibmcclient
Keywords: HUAWEI iBMC redfish API client
Platform: UNKNOWN
Classifier: Development Status :: 4 - Beta
Classifier: Intended Audience :: Developers
Classifier: Intended Audience :: System Administrators
Classifier: Operating System :: OS Independent
Classifier: Topic :: Software Development :: Libraries :: Python Modules
Classifier: License :: OSI Approved :: Apache Software License
Classifier: Programming Language :: Python
Classifier: Programming Language :: Python :: 2
Classifier: Programming Language :: Python :: 2.7
Classifier: Programming Language :: Python :: 3
Classifier: Programming Language :: Python :: 3.4
Classifier: Programming Language :: Python :: 3.5
Classifier: Programming Language :: Python :: 3.6
Classifier: Programming Language :: Python :: 3.7
Requires-Dist: requests (>=2.14.2)
Requires-Dist: six (>=1.10.0)
Requires-Dist: typing ; python_version < "3.5"
Provides-Extra: dev
Requires-Dist: check-manifest ; extra == 'dev'
Requires-Dist: flake8 ; extra == 'dev'
Provides-Extra: test
Requires-Dist: coverage ; extra == 'test'
